questra_meta/__init__.py
seven2one_questra-0.7.1.dist-info/METADATA
seven2one_questra-0.7.1.dist-info/WHEEL
seven2one_questra-0.7.1.dist-info/RECORD
