Metadata-Version: 2.4
Name: seven2one-questra
Version: 0.7.1
Summary: Unified Python Client für Questra Platform - Umbrella Package für Authentication und Data API
Author-email: Jürgen Talasch <juergen.talasch@seven2one.de>
License: Proprietary
Classifier: Development Status :: 4 - Beta
Classifier: Intended Audience :: Developers
Classifier: Intended Audience :: Information Technology
Classifier: Intended Audience :: Science/Research
Classifier: License :: Other/Proprietary License
Classifier: Programming Language :: Python :: 3
Classifier: Programming Language :: Python :: 3.10
Classifier: Programming Language :: Python :: 3.11
Classifier: Programming Language :: Python :: 3.12
Classifier: Programming Language :: Python :: 3.13
Classifier: Programming Language :: Python :: 3.14
Classifier: Topic :: Database
Classifier: Topic :: Scientific/Engineering :: Information Analysis
Classifier: Topic :: Software Development :: Libraries :: Python Modules
Classifier: Typing :: Typed
Requires-Python: >=3.10
Requires-Dist: seven2one-questra-authentication>=0.3.0
Requires-Dist: seven2one-questra-automation>=0.3.0
Requires-Dist: seven2one-questra-data>=0.8.1
